cortisol/__init__.py
cortisol/commands/__init__.py
cortisol/commands/logs.py
cortisol/cortisollib/__init__.py
cortisol/cortisollib/calculators.py
cortisol/cortisollib/estimators.py
cortisol/cortisollib/hooks.py
cortisol/cortisollib/log_cost_estimator.py
cortisol/cortisollib/readers.py
cortisol/cortisollib/templates/cli_loadtest.py.j2
cortisol/cortisollib/users.py
cortisol/main.py
cortisol-0.3.0.dist-info/LICENSE
cortisol-0.3.0.dist-info/METADATA
cortisol-0.3.0.dist-info/WHEEL
cortisol-0.3.0.dist-info/entry_points.txt
cortisol-0.3.0.dist-info/RECORD
