Metadata-Version: 2.1
Name: cortisol
Version: 0.3.0
Summary: Accurately forecast log costs pre-production with Cortisol for Datadog, New Relic, and Grafana 💰📉
License: Apache-2.0
Author: pm3310
Author-email: pavlos@cortisol.ai
Requires-Python: >=3.8,<4.0
Classifier: License :: OSI Approved :: Apache Software License
Classifier: Programming Language :: Python :: 3
Classifier: Programming Language :: Python :: 3.8
Classifier: Programming Language :: Python :: 3.9
Classifier: Programming Language :: Python :: 3.10
Classifier: Programming Language :: Python :: 3.11
Requires-Dist: docker (>=6.1.3,<7.0.0)
Requires-Dist: jinja2 (>=3.1.2,<4.0.0)
Requires-Dist: locust (>=2.16.0,<3.0.0)
Requires-Dist: prettytable (>=3.8.0,<4.0.0)
Requires-Dist: pyyaml (>=6.0.1,<7.0.0)
Requires-Dist: typer[all] (>=0.9.0,<0.10.0)
